funny_clustering/__init__.py
funny_clustering/cluster_count_analyse.py
funny_clustering/clustering.py
funny_clustering-0.2.dist-info/METADATA
funny_clustering-0.2.dist-info/WHEEL
funny_clustering-0.2.dist-info/top_level.txt
funny_clustering-0.2.dist-info/RECORD
