Metadata-Version: 2.1
Name: funny-clustering
Version: 0.2
Summary: UNKNOWN
Home-page: UNKNOWN
Author: Igor Tereshchenko
Author-email: tereshchenko.igor@gmail.com
License: UNKNOWN
Platform: UNKNOWN
Classifier: Programming Language :: Python :: 3
Classifier: License :: OSI Approved :: MIT License
Classifier: Operating System :: OS Independent
Requires-Dist: certifi (==2021.10.8)
Requires-Dist: charset-normalizer (==2.0.7)
Requires-Dist: cycler (==0.10.0)
Requires-Dist: embeddings (==0.0.8)
Requires-Dist: idna (==3.3)
Requires-Dist: joblib (==1.1.0)
Requires-Dist: kiwisolver (==1.3.2)
Requires-Dist: matplotlib (==3.4.3)
Requires-Dist: numpy (==1.21.3)
Requires-Dist: pandas (==1.3.4)
Requires-Dist: Pillow (==8.4.0)
Requires-Dist: pyparsing (==3.0.0)
Requires-Dist: python-dateutil (==2.8.2)
Requires-Dist: pytz (==2021.3)
Requires-Dist: requests (==2.26.0)
Requires-Dist: scikit-learn (==1.0)
Requires-Dist: scipy (==1.7.1)
Requires-Dist: six (==1.16.0)
Requires-Dist: sklearn (==0.0)
Requires-Dist: threadpoolctl (==3.0.0)
Requires-Dist: tqdm (==4.62.3)
Requires-Dist: urllib3 (==1.26.7)
